excellaint/__init__.py
excellaint/excellaint.py
excellaint-0.1.0.dist-info/LICENSE
excellaint-0.1.0.dist-info/METADATA
excellaint-0.1.0.dist-info/WHEEL
excellaint-0.1.0.dist-info/entry_points.txt
excellaint-0.1.0.dist-info/top_level.txt
excellaint-0.1.0.dist-info/RECORD
