Metadata-Version: 2.1
Name: excellaint
Version: 0.1.0
Summary: A Python toolbox for dealing with some of the oddities that Excel can introduce into your dates.
Author-email: Charles Turner <charlesturner0987@gmail.com>
License: MIT License
Project-URL: homepage, https://github.com/charles-turner-1/ExcellAint
Classifier: License :: OSI Approved :: MIT License
Classifier: Programming Language :: Python :: 3
License-File: LICENSE
Requires-Dist: polars >=0.20
Requires-Dist: inquirer >=3.2
Requires-Dist: pandas >=1.3
Requires-Dist: fastexcel >=0.10.3
Requires-Dist: pyarrow >=15.0
Requires-Dist: xlsx2csv >=0.8
Provides-Extra: dev
Requires-Dist: pytest >=3.7 ; extra == 'dev'
